.gitignore
AUTHORS
NEWS.txt
README.txt
TODO.txt
paste_deploy_config.ini_tmpl
setup.cfg
setup.py
gazest_extra_macros/__init__.py
gazest_extra_macros/asciidoc_macros.py
gazest_extra_macros/bbcode.py
gazest_extra_macros/echo.py
gazest_extra_macros/markdown_macros.py
gazest_extra_macros/math.py
gazest_extra_macros/postmarkup.py
gazest_extra_macros/rst.py
gazest_extra_macros/social.py
gazest_extra_macros/textile_macros.py
gazest_extra_macros/util.py
gazest_extra_macros.egg-info/PKG-INFO
gazest_extra_macros.egg-info/SOURCES.txt
gazest_extra_macros.egg-info/dependency_links.txt
gazest_extra_macros.egg-info/entry_points.txt
gazest_extra_macros.egg-info/paste_deploy_config.ini_tmpl
gazest_extra_macros.egg-info/requires.txt
gazest_extra_macros.egg-info/top_level.txt
