Metadata-Version: 1.0
Name: gazest-extra-macros
Version: 0.3.1
Summary: extra wiki macros for gazest
Home-page: UNKNOWN
Author: Yannick Gingras
Author-email: ygingras@ygingras.net
License: GPL v3 or later
Platform: UNKNOWN
